departmentscrape
