Metadata-Version: 1.0
Name: departmentscrape
Version: 0.2a2dev
Summary: little tool I use at work until we can get this done the right way
Home-page: http://github.com/ralphbean/departmentscrape
Author: Ralph Bean
Author-email: ralph.bean@gmail.com
License: GPL
Platform: UNKNOWN
Classifier: Development Status :: 3 - Alpha
Classifier: Topic :: Software Development :: Libraries :: Python Modules
